setup.py
demo/__init__.py
demo/admin.py
demo/base.py
demo/context_processor.py
demo/exceptions.py
demo/middleware.py
demo/models.py
demo/router.py
demo/settings.py
demo/shared.py
demo/tests.py
demo/backends/__init__.py
demo/backends/mysql/__init__.py
demo/backends/mysql/backend.py
demo/backends/postgresql_psycopg2/__init__.py
demo/backends/postgresql_psycopg2/backend.py
demo/backends/sqlite3/__init__.py
demo/backends/sqlite3/backend.py
demo/management/__init__.py
demo/management/commands/__init__.py
demo/management/commands/cleandemos.py
demo/migrations/0001_initial.py
demo/migrations/0002_auto__add_session.py
demo/migrations/0003_move_to_sesssion.py
demo/migrations/0004_auto__del_field_sessiondatabase_session.py
demo/migrations/__init__.py
demo_controller/__init__.py
demo_controller/admin.py
demo_controller/models.py
django_demo.egg-info/PKG-INFO
django_demo.egg-info/SOURCES.txt
django_demo.egg-info/dependency_links.txt
django_demo.egg-info/not-zip-safe
django_demo.egg-info/top_level.txt